apache_airflow_granulate_databricks/__init__.py
apache_airflow_granulate_databricks/granulate_plugin.py
apache_airflow_granulate_databricks-0.2.1.dist-info/LICENSE
apache_airflow_granulate_databricks-0.2.1.dist-info/METADATA
apache_airflow_granulate_databricks-0.2.1.dist-info/WHEEL
apache_airflow_granulate_databricks-0.2.1.dist-info/entry_points.txt
apache_airflow_granulate_databricks-0.2.1.dist-info/RECORD
