Metadata-Version: 2.1
Name: apache-airflow-granulate-databricks
Version: 0.2.1
Summary: The Granulate Airflow-Databricks Integration is an open-source plugin for Apache Airflow. It's specifically designed to set environment variables that allow Granulate's performance monitoring agent to identify and integrate with Databricks jobs orchestrated by Airflow. This plugin tags Databricks jobs, aiding the Granulate optimizing agent.
License: LICENSE
Author: Granulate
Author-email: databricks.publisher@granulate.io
Requires-Python: >=3.8,<3.13
Classifier: License :: Other/Proprietary License
Classifier: Programming Language :: Python :: 3
Classifier: Programming Language :: Python :: 3.8
Classifier: Programming Language :: Python :: 3.9
Classifier: Programming Language :: Python :: 3.10
Classifier: Programming Language :: Python :: 3.11
Classifier: Programming Language :: Python :: 3.12
Provides-Extra: auto-patch
Requires-Dist: apache-airflow-granulate-databricks-auto-patch (==0.1.0) ; extra == "auto-patch"
Requires-Dist: docutils (!=0.21)
Requires-Dist: importlib-metadata
